azure_activation_service/__init__.py
azure_activation_service/cli.py
azure_activation_service/config.py
azure_activation_service/pim_client.py
azure_activation_service-0.2.1.dist-info/LICENSE
azure_activation_service-0.2.1.dist-info/METADATA
azure_activation_service-0.2.1.dist-info/WHEEL
azure_activation_service-0.2.1.dist-info/entry_points.txt
azure_activation_service-0.2.1.dist-info/top_level.txt
azure_activation_service-0.2.1.dist-info/RECORD
