Metadata-Version: 2.2
Name: azure-activation-service
Version: 0.2.1
Summary: Auto Activate Azure Roles
Author-email: NCJ <author@example.com>
License: MIT License
Requires-Python: >=3.8
License-File: LICENSE
Requires-Dist: requests
Requires-Dist: azure-identity
Requires-Dist: click>=8.0.0
Requires-Dist: tabulate
